quantiphyse/__init__.py
quantiphyse/_version.py
quantiphyse/qpmain.py
quantiphyse/data/__init__.py
quantiphyse/data/dicoms.py
quantiphyse/data/extras.py
quantiphyse/data/functions.py
quantiphyse/data/load_save.py
quantiphyse/data/nifti.py
quantiphyse/data/qpdata.py
quantiphyse/data/volume_management.py
quantiphyse/gui/HistogramWidget.py
quantiphyse/gui/ImageView.py
quantiphyse/gui/MainWindow.py
quantiphyse/gui/OrthoDataView.py
quantiphyse/gui/Register.py
quantiphyse/gui/ViewOptions.py
quantiphyse/gui/__init__.py
quantiphyse/gui/data_views.py
quantiphyse/gui/dialogs.py
quantiphyse/gui/options.py
quantiphyse/gui/pickers.py
quantiphyse/gui/plot.py
quantiphyse/gui/widgets.py
quantiphyse/icons/__init__.py
quantiphyse/icons/batch.png
quantiphyse/icons/batch.svg
quantiphyse/icons/bucket.png
quantiphyse/icons/bucket.svg
quantiphyse/icons/cest.png
quantiphyse/icons/cest.svg
quantiphyse/icons/citation.png
quantiphyse/icons/citation.svg
quantiphyse/icons/clear.png
quantiphyse/icons/clear.svg
quantiphyse/icons/close.png
quantiphyse/icons/close.svg
quantiphyse/icons/clustering.png
quantiphyse/icons/clustering.svg
quantiphyse/icons/compare.png
quantiphyse/icons/compare.svg
quantiphyse/icons/console.png
quantiphyse/icons/console.svg
quantiphyse/icons/crosshairs.png
quantiphyse/icons/crosshairs.svg
quantiphyse/icons/curve_view.png
quantiphyse/icons/curve_view.svg
quantiphyse/icons/data.png
quantiphyse/icons/data.svg
quantiphyse/icons/double_icon.svg
quantiphyse/icons/double_icon_store.png
quantiphyse/icons/down.png
quantiphyse/icons/down.svg
quantiphyse/icons/edit.png
quantiphyse/icons/edit.svg
quantiphyse/icons/ellipse.png
quantiphyse/icons/ellipse.svg
quantiphyse/icons/eraser.png
quantiphyse/icons/eraser.svg
quantiphyse/icons/fabber_usage.svg
quantiphyse/icons/image_export.png
quantiphyse/icons/image_export.svg
quantiphyse/icons/inspect.png
quantiphyse/icons/inspect.svg
quantiphyse/icons/levels.png
quantiphyse/icons/levels.svg
quantiphyse/icons/main_data.png
quantiphyse-0.7.7.dist-info/LICENSE
quantiphyse-0.7.7.dist-info/METADATA
quantiphyse-0.7.7.dist-info/WHEEL
quantiphyse-0.7.7.dist-info/entry_points.txt
quantiphyse-0.7.7.dist-info/licence.docx
quantiphyse-0.7.7.dist-info/top_level.txt
quantiphyse-0.7.7.dist-info/RECORD
