Metadata-Version: 2.1
Name: quantiphyse
Version: 0.7.7
Summary: Quantiphyse is a data viewer and analysis platform for volumetric medical imaging data
Home-page: https://quantiphyse.readthedocs.io/
Author: Martin Craig
Author-email: martin.craig@eng.ox.ac.uk
License: License granted by University of Oxford for use by academics carrying out research and not for use by consumers or commercial businesses. See LICENSE file for more details
Platform: UNKNOWN
Classifier: Development Status :: 3 - Alpha
Classifier: Intended Audience :: Science/Research
Classifier: Programming Language :: Python :: 2.7
Classifier: Programming Language :: Python :: 3
Classifier: Topic :: Scientific/Engineering :: Bio-Informatics
Classifier: License :: Free for non-commercial use
Requires-Dist: Cython
Requires-Dist: funcsigs
Requires-Dist: matplotlib
Requires-Dist: nibabel
Requires-Dist: numpy
Requires-Dist: Pillow
Requires-Dist: pyqtgraph
Requires-Dist: PySide
Requires-Dist: PyYAML
Requires-Dist: requests
Requires-Dist: scipy
Requires-Dist: scikit-learn
Requires-Dist: scikit-image
Requires-Dist: setuptools
Requires-Dist: six
Requires-Dist: deprecation
Requires-Dist: pandas
